pylint_fastapi_plugin/__init__.py
pylint_fastapi_plugin/checker.py
pylint_fastapi_plugin/messages.py
pylint_fastapi_plugin/rules.py
pylint_fastapi_plugin-0.2.0.dist-info/METADATA
pylint_fastapi_plugin-0.2.0.dist-info/WHEEL
pylint_fastapi_plugin-0.2.0.dist-info/entry_points.txt
pylint_fastapi_plugin-0.2.0.dist-info/RECORD
