Metadata-Version: 2.1
Name: pylint-fastapi-plugin
Version: 0.2.0
Summary: A Pylint plugin that enforces FastAPI router decorator and model conventions
License: MIT
Keywords: pylint,fastapi,plugin,lint
Author: Your Name
Author-email: you@example.com
Requires-Python: >=3.8,<4.0
Classifier: License :: OSI Approved :: MIT License
Classifier: Programming Language :: Python :: 3
Classifier: Programming Language :: Python :: 3.8
Classifier: Programming Language :: Python :: 3.9
Classifier: Programming Language :: Python :: 3.10
Classifier: Programming Language :: Python :: 3.11
Classifier: Programming Language :: Python :: 3.12
Classifier: Programming Language :: Python :: 3.13
Classifier: Topic :: Software Development :: Quality Assurance
Requires-Dist: astroid (>=3.0.0,<4.0.0)
Requires-Dist: pylint (>=3.0.0,<4.0.0)
